contexter/__init__.py
contexter/cli.py
contexter/core/__init__.py
contexter/core/config.py
contexter/core/ctx.py
contexter/core/manifest.py
contexter/core/prompt.py
contexter/core/slicer.py
contexter/utils/__init__.py
contexter/utils/clipboard.py
contexter/utils/files.py
contexter/utils/git.py
contexter_codex-0.1.0.dist-info/METADATA
contexter_codex-0.1.0.dist-info/WHEEL
contexter_codex-0.1.0.dist-info/entry_points.txt
contexter_codex-0.1.0.dist-info/RECORD
